scrcpy/__init__.py
scrcpy/const.py
scrcpy/control.py
scrcpy/core.py
scrcpy/scrcpy-server.jar
scrcpy_core-0.0.7.dist-info/LICENSE.txt
scrcpy_core-0.0.7.dist-info/METADATA
scrcpy_core-0.0.7.dist-info/WHEEL
scrcpy_core-0.0.7.dist-info/top_level.txt
scrcpy_core-0.0.7.dist-info/RECORD
