Metadata-Version: 2.1
Name: scrcpy-core
Version: 0.0.7
Author: mortal_sjh
Author-email: mortal_sjh@qq.com
Requires-Python: >=3.9
License-File: LICENSE.txt
Requires-Dist: numpy==1.26.4
Requires-Dist: av==14.0.1
Requires-Dist: adbutils==2.8.0
